Design.v
`timescale 1ns / 1ps

module jCounter(
input clk_i, 
input ori_i, //overriding input(s) [used for Reset in this design]
output reg [3:0]dout_o
);

always@(posedge clk_i) begin
   if(ori_i) begin
      dout_o <= 4'b0000;
   end
   else begin
      dout_o <= {~dout_o[0], dout_o[3:1]};
   end
end

endmodule

Testbench.v
`timescale 1ns / 1ps

module tb_jCounter();
reg clk_ti;
reg ori_ti; 
wire [3:0]dout_to;

//instantiation
jCounter DUT(.clk_i(clk_ti), 
   .ori_i(ori_ti), 
   .dout_o(dout_to));

//clock
initial begin
   clk_ti = 1'b0;
   forever
      #5 clk_ti = ~clk_ti;
end

//feeding
initial begin
ori_ti = 1'b1;
#10 ori_ti = 1'b0;
#180 ori_ti = 1'b1;
#25 ori_ti = 1'b0;
#10 $finish;
end

//capture
initial begin
$monitor("Time: %0t | ORI: %b, Clk: %b | Count: %b", $time, ori_ti, clk_ti, dout_to);
$dumpfile("jCounter.vcd");
$dumpvars(0, tb_jCounter);
end

endmodule

jCounter.vcd
$date
   Sun Apr 26 13:21:04 2026
$end

$version
  2025.2
  $dumpfile ("jCounter.vcd") 
$end

$timescale
  1ps
$end

$scope module tb_jCounter $end
$var reg 1 ! clk_ti $end
$var reg 1 " ori_ti $end
$var wire 4 # dout_to [3:0] $end
$scope module DUT $end
$var wire 1 $ clk_i $end
$var wire 1 % ori_i $end
$var reg 4 & dout_o [3:0] $end
$upscope $end
$upscope $end
$enddefinitions $end

#0
$dumpvars
0!
1"
bx #
0$
1%
bx &
$end

#5000
1!
b0 #
1$
b0 &

#10000
0!
0"
0$
0%

#15000
1!
b1000 #
1$
b1000 &

#20000
0!
0$

#25000
1!
b1100 #
1$
b1100 &

#30000
0!
0$

#35000
1!
b1110 #
1$
b1110 &

#40000
0!
0$

#45000
1!
b1111 #
1$
b1111 &

#50000
0!
0$

#55000
1!
b111 #
1$
b111 &

#60000
0!
0$

#65000
1!
b11 #
1$
b11 &

#70000
0!
0$

#75000
1!
b1 #
1$
b1 &

#80000
0!
0$

#85000
1!
b0 #
1$
b0 &

#90000
0!
0$

#95000
1!
b1000 #
1$
b1000 &

#100000
0!
0$

#105000
1!
b1100 #
1$
b1100 &

#110000
0!
0$

#115000
1!
b1110 #
1$
b1110 &

#120000
0!
0$

#125000
1!
b1111 #
1$
b1111 &

#130000
0!
0$

#135000
1!
b111 #
1$
b111 &

#140000
0!
0$

#145000
1!
b11 #
1$
b11 &

#150000
0!
0$

#155000
1!
b1 #
1$
b1 &

#160000
0!
0$

#165000
1!
b0 #
1$
b0 &

#170000
0!
0$

#175000
1!
b1000 #
1$
b1000 &

#180000
0!
0$

#185000
1!
b1100 #
1$
b1100 &

#190000
0!
1"
0$
1%

#195000
1!
b0 #
1$
b0 &

#200000
0!
0$

#205000
1!
1$

#210000
0!
0$

#215000
1!
0"
b1000 #
1$
0%
b1000 &

